coinbasev2/__init__.py
coinbasev2/wallet/__init__.py
coinbasev2/wallet/auth.py
coinbasev2/wallet/client.py
coinbasev2/wallet/compat.py
coinbasev2/wallet/error.py
coinbasev2/wallet/model.py
coinbasev2/wallet/util.py
python_coinbasev2-2.1.0.dist-info/METADATA
python_coinbasev2-2.1.0.dist-info/WHEEL
python_coinbasev2-2.1.0.dist-info/top_level.txt
python_coinbasev2-2.1.0.dist-info/RECORD
