Metadata-Version: 2.1
Name: python-coinbasev2
Version: 2.1.0
Summary: Coinbase API client library
Home-page: https://github.com/coinbase/coinbase-python/
License: UNKNOWN
Download-URL: https://github.com/coinbase/coinbase-python/tarball/2.1.0
Keywords: api,coinbase,bitcoin,oauth2,client
Platform: UNKNOWN
Classifier: Intended Audience :: Developers
Classifier: License :: OSI Approved :: MIT License
Classifier: Operating System :: OS Independent
Classifier: Programming Language :: Python :: 2
Classifier: Programming Language :: Python :: 2.7
Classifier: Programming Language :: Python :: 3
Classifier: Programming Language :: Python :: 3.4
Classifier: Programming Language :: Python :: 3.5
Classifier: Programming Language :: Python :: 3.6
Classifier: Programming Language :: Python
Classifier: Topic :: Software Development :: Libraries :: Python Modules
Requires-Dist: requests (>=2.5)
Requires-Dist: six (>=1.9)
Requires-Dist: pycryptodome (>=3.4.11)
